cachemodel/__init__.py
cachemodel/decorators.py
cachemodel/managers.py
cachemodel/models.py
cachemodel/tests.py
cachemodel/utils.py
cachemodel/version.py
django_cachemodel-2.2.0.dist-info/LICENSE.md
django_cachemodel-2.2.0.dist-info/METADATA
django_cachemodel-2.2.0.dist-info/WHEEL
django_cachemodel-2.2.0.dist-info/top_level.txt
django_cachemodel-2.2.0.dist-info/RECORD
